dnax/io.py
dnax/losses.py
dnax/models/bpnet.py
dnax/models/chrombpnet.py
dnax/seq/utils.py
dnax/utils/train_utils.py
dnax-2024.0.0a1.dist-info/METADATA
dnax-2024.0.0a1.dist-info/WHEEL
dnax-2024.0.0a1.dist-info/licenses/LICENSE
dnax-2024.0.0a1.dist-info/RECORD
