Metadata-Version: 2.3
Name: dnax
Version: 2024.0.0a1
Summary: DNA models implemented in JAX
Project-URL: Repository, https://github.com/gtca/dnax.git
Project-URL: Bug Tracker, https://github.com/gtca/dnax/issues
Author-email: Danila Bredikhin <danila@stanford.edu>
Maintainer-email: Danila Bredikhin <danila@stanford.edu>
License: BSD3
Keywords: ATAC,CNN,DNA,chromatin
Classifier: Development Status :: 3 - Alpha
Classifier: Intended Audience :: Science/Research
Classifier: License :: OSI Approved :: BSD License
Classifier: Operating System :: OS Independent
Classifier: Programming Language :: Python :: 3
Classifier: Programming Language :: Python :: 3.10
Classifier: Programming Language :: Python :: 3.11
Classifier: Programming Language :: Python :: 3.12
Classifier: Topic :: Scientific/Engineering :: Bio-Informatics
Requires-Python: >=3.10
Requires-Dist: flax
Requires-Dist: jax
Requires-Dist: optax
Provides-Extra: test
Requires-Dist: pytest; extra == 'test'
Requires-Dist: tensorflow; extra == 'test'
Requires-Dist: tensorflow-probability; extra == 'test'
Requires-Dist: torch; extra == 'test'
